mahdijadaliha
