Metadata-Version: 2.1
Name: mahdijadaliha
Version: 0.21
Summary: highlights keywords syntax, and use template files to generate code
Home-page: https://db2sql.com/snippy
Author: Mahdi Jadaliha
Author-email: jadaliha@gmail.com
License: MIT
Platform: UNKNOWN
